setup.py
inoon_mgi_lib.egg-info/PKG-INFO
inoon_mgi_lib.egg-info/SOURCES.txt
inoon_mgi_lib.egg-info/dependency_links.txt
inoon_mgi_lib.egg-info/entry_points.txt
inoon_mgi_lib.egg-info/top_level.txt
mgi_lib/__init__.py
mgi_lib/api.py
mgi_lib/auth.py
mgi_lib/dev.py
mgi_lib/errs.py
mgi_lib/me.py