Metadata-Version: 1.0
Name: inoon-mgi-lib
Version: 0.2.0
Summary: Ino-Vibe API library.
Home-page: UNKNOWN
Author: Joonkyo Kim
Author-email: jkkim@ino-on.com
License: UNKNOWN
Platform: UNKNOWN
